canopen_monitor/__init__.py
canopen_monitor/__main__.py
canopen_monitor/app.py
canopen_monitor/meta.py
canopen_monitor/can/__init__.py
canopen_monitor/can/interface.py
canopen_monitor/can/magic_can_bus.py
canopen_monitor/can/message.py
canopen_monitor/can/message_table.py
canopen_monitor/parse/__init__.py
canopen_monitor/parse/canopen.py
canopen_monitor/parse/eds.py
canopen_monitor/parse/emcy.py
canopen_monitor/parse/hb.py
canopen_monitor/parse/pdo.py
canopen_monitor/parse/sdo.py
canopen_monitor/parse/sync.py
canopen_monitor/parse/time.py
canopen_monitor/parse/utilities.py
canopen_monitor/ui/__init__.py
canopen_monitor/ui/colum.py
canopen_monitor/ui/grid.py
canopen_monitor/ui/message_pane.py
canopen_monitor/ui/pane.py
canopen_monitor/ui/windows.py
tests/__init__.py
tests/spec_eds_parser.py
tests/spec_emcy_parser.py
tests/spec_hb_parser.py
tests/spec_interface.py
tests/spec_magic_can_bus.py
tests/spec_meta.py
tests/spec_pdo_parser.py
tests/spec_sdo_parser.py
tests/spec_sync_parser.py
tests/spec_time_parser.py
canopen_monitor-4.1.0.dist-info/LICENSE
canopen_monitor-4.1.0.dist-info/METADATA
canopen_monitor-4.1.0.dist-info/WHEEL
canopen_monitor-4.1.0.dist-info/entry_points.txt
canopen_monitor-4.1.0.dist-info/top_level.txt
canopen_monitor-4.1.0.dist-info/RECORD
