Metadata-Version: 2.1
Name: canopen-monitor
Version: 4.1.0
Summary: An NCurses-based TUI application for tracking activity over the CAN bus and decoding messages with provided EDS/OD files.
Home-page: https://github.com/oresat/CANopen-monitor
Author: Dmitri McGuckin
Maintainer: Portland State Aerospace Society
Maintainer-email: oresat@pdx.edu
License: GPL-3.0
Project-URL: Documentation, https://canopen-monitor.readthedocs.io
Project-URL: Bug Tracking, https://github.com/oresat/CANopen-monitor/issues?q=is%3Aopen+is%3Aissue+label%3Abug
Platform: UNKNOWN
Classifier: Programming Language :: Python :: 3
Classifier: License :: OSI Approved :: GNU General Public License v3 (GPLv3)
Classifier: Operating System :: OS Independent
Classifier: Environment :: Console :: Curses
Classifier: Topic :: Scientific/Engineering :: Information Analysis
Classifier: Topic :: Software Development :: User Interfaces
Classifier: Topic :: System :: Monitoring
Classifier: Topic :: System :: Networking :: Monitoring :: Hardware Watchdog
Requires-Python: >=3.9.0
License-File: LICENSE
Requires-Dist: pyvit (>=0.2.1)
Requires-Dist: psutil (>=5.8.0)
Requires-Dist: python-dateutil (>=2.8.1)
Provides-Extra: dev
Requires-Dist: python-can ; extra == 'dev'
Requires-Dist: setuptools ; extra == 'dev'
Requires-Dist: wheel ; extra == 'dev'
Requires-Dist: flake8 ; extra == 'dev'
Requires-Dist: twine ; extra == 'dev'
Requires-Dist: sphinx ; extra == 'dev'
Requires-Dist: sphinx-rtd-theme ; extra == 'dev'
